ghstats_cli/__init__.py
ghstats_cli/cli.py
ghstats_cli/config.py
ghstats_cli/heatmap.py
ghstats_cli-0.1.0.dist-info/licenses/LICENSE
ghstats_cli-0.1.0.dist-info/METADATA
ghstats_cli-0.1.0.dist-info/WHEEL
ghstats_cli-0.1.0.dist-info/entry_points.txt
ghstats_cli-0.1.0.dist-info/top_level.txt
ghstats_cli-0.1.0.dist-info/RECORD
