Metadata-Version: 2.4
Name: ghstats-cli
Version: 0.1.0
Summary: A CLI to display your GitHub contributions heatmap, streaks, and activity over the past year.
Author-email: Darshan Paccha <darshan.paccha@gmail.com>
License-Expression: MIT
Project-URL: Homepage, https://github.com/d1rshan/ghstats-cli
Project-URL: Bug Tracker, https://github.com/d1rshan/ghstats-cli/issues
Project-URL: Maintainer, https://github.com/d1rshan
Keywords: GitHub,CLI,contributions,streaks,heatmap
Classifier: Development Status :: 4 - Beta
Classifier: Programming Language :: Python :: 3
Classifier: Operating System :: OS Independent
Classifier: Environment :: Console
Classifier: Intended Audience :: Developers
Classifier: Topic :: Terminals
Classifier: Topic :: Utilities
Requires-Python: >=3.8
License-File: LICENSE
Requires-Dist: click
Requires-Dist: requests
Requires-Dist: rich
Dynamic: license-file
